cemento/__init__.py
cemento/main.py
cemento/axioms/__init__.py
cemento/axioms/constants.py
cemento/axioms/extract_axioms.py
cemento/axioms/modules/__init__.py
cemento/axioms/modules/ms.py
cemento/cli/__init__.py
cemento/cli/constants.py
cemento/cli/download.py
cemento/cli/drawio_rdf.py
cemento/cli/drawio_ttl.py
cemento/cli/rdf_drawio.py
cemento/cli/ttl_drawio.py
cemento/data/default_prefixes.json
cemento/data/defaults/owl.ttl
cemento/data/defaults/rdf.ttl
cemento/data/defaults/rdfs.ttl
cemento/data/references/cco.ttl
cemento/data/reserved/ms.ttl
cemento/draw_io/__init__.py
cemento/draw_io/constants.py
cemento/draw_io/io.py
cemento/draw_io/preprocessing.py
cemento/draw_io/read_diagram.py
cemento/draw_io/transforms.py
cemento/draw_io/write_diagram.py
cemento/rdf/__init__.py
cemento/rdf/constants.py
cemento/rdf/drawio_to_rdf.py
cemento/rdf/io.py
cemento/rdf/preprocessing.py
cemento/rdf/rdf_to_drawio.py
cemento/rdf/rdf_to_graph.py
cemento/rdf/transforms.py
cemento/templates/circle.xml
cemento/templates/class.xml
cemento/templates/connector.xml
cemento/templates/instance.xml
cemento/templates/line.xml
cemento/templates/literal.xml
cemento/templates/scaffold.xml
cemento/templates/shape.xml
cemento/term_matching/constants.py
cemento/term_matching/io.py
cemento/term_matching/preprocessing.py
cemento/term_matching/transforms.py
cemento/utils/__init__.py
cemento/utils/constants.py
cemento/utils/io.py
cemento/utils/utils.py
cemento-0.13.0.dist-info/licenses/LICENSE.md
cemento-0.13.0.dist-info/METADATA
cemento-0.13.0.dist-info/WHEEL
cemento-0.13.0.dist-info/entry_points.txt
cemento-0.13.0.dist-info/top_level.txt
cemento-0.13.0.dist-info/RECORD
