Metadata-Version: 2.4
Name: cemento
Version: 0.13.0
Summary: A package to view and write ontologies directly from draw.io diagram files.
Author-email: Gabriel Obsequio Ponon <gop2@case.edu>
License: BSD-3-Clause
Project-URL: Homepage, https://cwru-sdle.github.io/CEMENTO/
Classifier: Programming Language :: Python :: 3
Classifier: Operating System :: OS Independent
Requires-Python: >=3.10
License-File: LICENSE.md
Requires-Dist: beautifulsoup4
Requires-Dist: defusedxml
Requires-Dist: networkx
Requires-Dist: pandas
Requires-Dist: rdflib
Requires-Dist: thefuzz
Requires-Dist: tldextract
Requires-Dist: more-itertools
Dynamic: license-file
